epikgameringrecaptchasolver/__init__.py
epikgameringrecaptchasolver/components.py
epikgameringrecaptchasolver-0.2.0.dist-info/METADATA
epikgameringrecaptchasolver-0.2.0.dist-info/WHEEL
epikgameringrecaptchasolver-0.2.0.dist-info/top_level.txt
epikgameringrecaptchasolver-0.2.0.dist-info/RECORD
