Metadata-Version: 2.1
Name: epikgameringrecaptchasolver
Version: 0.2.0
Summary: c2FsdCByZWNhcHRjaGEgc29sdmVyIHZlcnNpb24xIA==
Home-page: https://github.com/usesalt/epikgameringrecaptchasolver
Author: bob/salt
Author-email: aimloqrtamar@gmail.com
License: None
Classifier: Development Status :: 1 - Planning
Classifier: Intended Audience :: Science/Research
Classifier: License :: OSI Approved :: BSD License
Classifier: Operating System :: POSIX :: Linux
Classifier: Programming Language :: Python :: 2
Classifier: Programming Language :: Python :: 2.7
Classifier: Programming Language :: Python :: 3
Classifier: Programming Language :: Python :: 3.4
Classifier: Programming Language :: Python :: 3.5
Requires-Dist: SpeechRecognition
Requires-Dist: selenium
